datepick
